[
  {
    "debut": "2025-09",
    "fin": "present",
    "poste": "Développeur Front",
    "nom": "Société Générale",
    "lieu": "La Défense (92)",
    "missions": [
      "Développement de l'application front en ReactJS",
      "Développement de la BFF en NestJS",
      "Mise en place de la CI/CD des applications",
      "Déploiements des applications"
    ]
  },
  {
    "debut": "2023-01",
    "fin": "2025-06",
    "poste": "Développeur Front ReactJS",
    "nom": "Primeum",
    "lieu": "Levallois-Perret (92)",
    "missions": [
      "Conception et maintenance d'un Design System",
      "Elaboration d'un Storybook et tests Jest des composants",
      "Réalisation d'une application de répartition des primes",
      "Mise en place d'une application de centralisation des services dans une architecture Back for Front",
      "Maquettes des interfaces"
    ]
  },
  {
    "debut": "2020-05",
    "fin": "2022-08",
    "poste": "Développeur Front Dataviz",
    "nom": "Fanvoice",
    "lieu": "Paris (75)",
    "missions": [
      "Création d'une application d'analyse sémantique (Dashboard sous D3.js)",
      "Mise à jour de pages web du site vitrine",
      "Intégration d'une API REST"
    ]
  }
]
